surfinpy/__init__.py
surfinpy/_fig_params.py
surfinpy/_testutils.py
surfinpy/bulk_mu_vs_mu.py
surfinpy/bulk_mu_vs_t.py
surfinpy/data.py
surfinpy/mu_vs_mu.py
surfinpy/p_vs_t.py
surfinpy/plotting.py
surfinpy/utils.py
surfinpy/vibrational_data.py
surfinpy/wulff.py
surfinpy-2.0.0.dist-info/METADATA
surfinpy-2.0.0.dist-info/WHEEL
surfinpy-2.0.0.dist-info/top_level.txt
surfinpy-2.0.0.dist-info/RECORD
