Metadata-Version: 2.1
Name: surfinpy
Version: 2.0.0
Summary: Surface Phase Diagram Plotting Tools
Home-page: https://github.com/symmy596/SurfinPy
Author: Adam R. Symington
Author-email: ars44@bath.ac.uk
License: MIT license
Platform: UNKNOWN
Classifier: Programming Language :: Python
Classifier: Development Status :: 5 - Production/Stable
Classifier: Intended Audience :: Science/Research
Classifier: Operating System :: OS Independent
Classifier: Topic :: Scientific/Engineering
Requires-Dist: scipy
Requires-Dist: numpy
Requires-Dist: jupyter
Requires-Dist: pymatgen
Requires-Dist: matplotlib
Requires-Dist: coverage
Requires-Dist: coveralls
Requires-Dist: seaborn
